{
   "meals": {
      "1454779968": {
         "mail": "pol@pol.pl",
         "date": "02.02.2021",
         "start": "09:30",
         "end": "10:15",
         "time": "00:45 h",
         "type": ["pierś", "butelka"]
      },
      "3783826922": {
         "mail": "kij@kij.pl",
         "date": "04.02.2021",
         "start": "11:15",
         "end": "12:15",
         "time": "01:00 h",
         "type": ["butelka", "mleko modyfikowane"]
      }
   },
   "users": {
      "823746238": {
         "mail": "pol@pol.pl",
         "babyBirthday": "17.10.2020"
      },
      "823526312": {
         "mail": "kij@kij.pl",
         "babyBirthday": "22.10.2020"
      }
   }
}
